{"checkpoints": [{"number": 0, "position": {"X": 1558.762, "Y": 6938.542, "Z": 1078.055, "_padding": 0}, "quaternion": {"W": 0.8933713883278376, "X": 0.0, "Y": 0.0, "Z": 0.4493189986158966}, "rndchk": false, "rndchks": false, "chs": 1.0, "position2": {"X": 0.0, "Y": 0.0, "Z": 0.0, "_padding": 0}, "quaternion2": {"W": 1.0, "X": 0.0, "Y": 0.0, "Z": 0.0}}, {"number": 1, "position": {"X": 1433.566, "Y": 7030.536, "Z": 1078.045, "_padding": 0}, "quaternion": {"W": 0.8933713883278376, "X": 0.0, "Y": 0.0, "Z": 0.4493189986158966}, "rndchk": false, "rndchks": false, "chs": 1.0, "position2": {"X": 0.0, "Y": 0.0, "Z": 0.0, "_padding": 0}, "quaternion2": {"W": 1.0, "X": 0.0, "Y": 0.0, "Z": 0.0}}, {"number": 2, "position": {"X": 1244.395, "Y": 7170.258, "Z": 1078.025, "_padding": 0}, "quaternion": {"W": 0.8933713883278376, "X": 0.0, "Y": 0.0, "Z": 0.4493189986158966}, "rndchk": false, "rndchks": false, "chs": 1.0, "position2": {"X": 0.0, "Y": 0.0, "Z": 0.0, "_padding": 0}, "quaternion2": {"W": 1.0, "X": 0.0, "Y": 0.0, "Z": 0.0}}, {"number": 3, "position": {"X": 1039.123, "Y": 7321.296, "Z": 1078.005, "_padding": 0}, "quaternion": {"W": 0.8933713883278376, "X": 0.0, "Y": 0.0, "Z": 0.4493189986158966}, "rndchk": false, "rndchks": false, "chs": 1.0, "position2": {"X": 0.0, "Y": 0.0, "Z": 0.0, "_padding": 0}, "quaternion2": {"W": 1.0, "X": 0.0, "Y": 0.0, "Z": 0.0}}, {"number": 4, "position": {"X": 723.027, "Y": 7472.968, "Z": 1187.481, "_padding": 0}, "quaternion": {"W": 0.3242476445475946, "X": 0.0, "Y": 0.0, "Z": 0.9459722326819835}, "rndchk": false, "rndchks": false, "chs": 1.0, "position2": {"X": 0.0, "Y": 0.0, "Z": 0.0, "_padding": 0}, "quaternion2": {"W": 1.0, "X": 0.0, "Y": 0.0, "Z": 0.0}}, {"number": 5, "position": {"X": 644.71, "Y": 7365.117, "Z": 1187.604, "_padding": 0}, "quaternion": {"W": 0.33274548119306463, "X": 0.0, "Y": 0.0, "Z": 0.9430166725703188}, "rndchk": false, "rndchks": false, "chs": 1.0, "position2": {"X": 0.0, "Y": 0.0, "Z": 0.0, "_padding": 0}, "quaternion2": {"W": 1.0, "X": 0.0, "Y": 0.0, "Z": 0.0}}, {"number": 6, "position": {"X": 544.332, "Y": 7199.919, "Z": 1178.694, "_padding": 0}, "quaternion": {"W": -0.08925066718848342, "X": 0.0, "Y": 0.0, "Z": 0.9960091959447014}, "rndchk": false, "rndchks": false, "chs": 1.0, "position2": {"X": 0.0, "Y": 0.0, "Z": 0.0, "_padding": 0}, "quaternion2": {"W": 1.0, "X": 0.0, "Y": 0.0, "Z": 0.0}}, {"number": 7, "position": {"X": 620.138, "Y": 7113.321, "Z": 1113.899, "_padding": 0}, "quaternion": {"W": -0.48218950593415344, "X": 0.0, "Y": 0.0, "Z": 0.876066938291234}, "rndchk": false, "rndchks": false, "chs": 1.0, "position2": {"X": 0.0, "Y": 0.0, "Z": 0.0, "_padding": 0}, "quaternion2": {"W": 1.0, "X": 0.0, "Y": 0.0, "Z": 0.0}}, {"number": 8, "position": {"X": 731.798, "Y": 7031.903, "Z": 1034.115, "_padding": 0}, "quaternion": {"W": -0.45704359485141, "X": 0.0, "Y": 0.0, "Z": 0.8894442941552327}, "rndchk": false, "rndchks": false, "chs": 1.0, "position2": {"X": 0.0, "Y": 0.0, "Z": 0.0, "_padding": 0}, "quaternion2": {"W": 1.0, "X": 0.0, "Y": 0.0, "Z": 0.0}}, {"number": 9, "position": {"X": 1016.212, "Y": 6826.995, "Z": 831.54, "_padding": 0}, "quaternion": {"W": -0.4671121093171099, "X": 0.0, "Y": 0.0, "Z": 0.8841980984651122}, "rndchk": false, "rndchks": false, "chs": 1.0, "position2": {"X": 0.0, "Y": 0.0, "Z": 0.0, "_padding": 0}, "quaternion2": {"W": 1.0, "X": 0.0, "Y": 0.0, "Z": 0.0}}, {"number": 10, "position": {"X": 1274.914, "Y": 6639.061, "Z": 647.068, "_padding": 0}, "quaternion": {"W": -0.46464114431993647, "X": 0.0, "Y": 0.0, "Z": 0.8854990722779217}, "rndchk": false, "rndchks": false, "chs": 1.0, "position2": {"X": 0.0, "Y": 0.0, "Z": 0.0, "_padding": 0}, "quaternion2": {"W": 1.0, "X": 0.0, "Y": 0.0, "Z": 0.0}}, {"number": 11, "position": {"X": 1668.467, "Y": 6355.245, "Z": 366.856, "_padding": 0}, "quaternion": {"W": -0.48141716098622017, "X": 0.0, "Y": 0.0, "Z": 0.8764915955717817}, "rndchk": false, "rndchks": false, "chs": 1.0, "position2": {"X": 0.0, "Y": 0.0, "Z": 0.0, "_padding": 0}, "quaternion2": {"W": 1.0, "X": 0.0, "Y": 0.0, "Z": 0.0}}, {"number": 12, "position": {"X": 1901.406, "Y": 6185.088, "Z": 200.325, "_padding": 0}, "quaternion": {"W": -0.45633712103119617, "X": 0.0, "Y": 0.0, "Z": 0.8898069633178645}, "rndchk": false, "rndchks": false, "chs": 1.0, "position2": {"X": 0.0, "Y": 0.0, "Z": 0.0, "_padding": 0}, "quaternion2": {"W": 1.0, "X": 0.0, "Y": 0.0, "Z": 0.0}}, {"number": 13, "position": {"X": 2186.802, "Y": 5973.731, "Z": 50.174, "_padding": 0}, "quaternion": {"W": -0.41881823204469865, "X": 0.0, "Y": 0.0, "Z": 0.9080700900849851}, "rndchk": false, "rndchks": false, "chs": 1.0, "position2": {"X": 0.0, "Y": 0.0, "Z": 0.0, "_padding": 0}, "quaternion2": {"W": 1.0, "X": 0.0, "Y": 0.0, "Z": 0.0}}, {"number": 14, "position": {"X": 2303.245, "Y": 5860.194, "Z": 46.777, "_padding": 0}, "quaternion": {"W": -0.35400540068010744, "X": 0.0, "Y": 0.0, "Z": 0.9352433781050346}, "rndchk": false, "rndchks": false, "chs": 1.0, "position2": {"X": 0.0, "Y": 0.0, "Z": 0.0, "_padding": 0}, "quaternion2": {"W": 1.0, "X": 0.0, "Y": 0.0, "Z": 0.0}}, {"number": 15, "position": {"X": 2634.015, "Y": 5372.007, "Z": 135.845, "_padding": 0}, "quaternion": {"W": -0.2785217847187402, "X": 0.0, "Y": 0.0, "Z": 0.9604299117775787}, "rndchk": false, "rndchks": false, "chs": 1.0, "position2": {"X": 0.0, "Y": 0.0, "Z": 0.0, "_padding": 0}, "quaternion2": {"W": 1.0, "X": 0.0, "Y": 0.0, "Z": 0.0}}, {"number": 16, "position": {"X": 2921.161, "Y": 4945.771, "Z": 179.767, "_padding": 0}, "quaternion": {"W": -0.28931582663076155, "X": 0.0, "Y": 0.0, "Z": 0.9572336979342919}, "rndchk": false, "rndchks": false, "chs": 1.0, "position2": {"X": 0.0, "Y": 0.0, "Z": 0.0, "_padding": 0}, "quaternion2": {"W": 1.0, "X": 0.0, "Y": 0.0, "Z": 0.0}}, {"number": 17, "position": {"X": 3096.67, "Y": 4755.895, "Z": 298.572, "_padding": 0}, "quaternion": {"W": -0.9149737536806012, "X": 0.0, "Y": 0.0, "Z": 0.40351335798908894}, "rndchk": false, "rndchks": false, "chs": 2.0, "position2": {"X": 0.0, "Y": 0.0, "Z": 0.0, "_padding": 0}, "quaternion2": {"W": 1.0, "X": 0.0, "Y": 0.0, "Z": 0.0}}, {"number": 18, "position": {"X": 3223.962, "Y": 4843.482, "Z": 297.006, "_padding": 0}, "quaternion": {"W": -0.8723765883353617, "X": 0.0, "Y": 0.0, "Z": 0.48883441790073956}, "rndchk": false, "rndchks": false, "chs": 1.0, "position2": {"X": 0.0, "Y": 0.0, "Z": 0.0, "_padding": 0}, "quaternion2": {"W": 1.0, "X": 0.0, "Y": 0.0, "Z": 0.0}}, {"number": 19, "position": {"X": 3326.313, "Y": 4915.697, "Z": 294.876, "_padding": 0}, "quaternion": {"W": -0.9795190598569934, "X": 0.0, "Y": 0.0, "Z": 0.20135146231619916}, "rndchk": false, "rndchks": false, "chs": 1.0, "position2": {"X": 0.0, "Y": 0.0, "Z": 0.0, "_padding": 0}, "quaternion2": {"W": 1.0, "X": 0.0, "Y": 0.0, "Z": 0.0}}, {"number": 20, "position": {"X": 3265.125, "Y": 5054.405, "Z": 232.434, "_padding": 0}, "quaternion": {"W": 0.9527092269019326, "X": 0.0, "Y": 0.0, "Z": 0.30388341345970493}, "rndchk": false, "rndchks": false, "chs": 1.0, "position2": {"X": 0.0, "Y": 0.0, "Z": 0.0, "_padding": 0}, "quaternion2": {"W": 1.0, "X": 0.0, "Y": 0.0, "Z": 0.0}}, {"number": 21, "position": {"X": 3194.928, "Y": 5159.806, "Z": 232.502, "_padding": 0}, "quaternion": {"W": 0.9592005581250752, "X": 0.0, "Y": 0.0, "Z": 0.28272652739448456}, "rndchk": false, "rndchks": false, "chs": 1.0, "position2": {"X": 0.0, "Y": 0.0, "Z": 0.0, "_padding": 0}, "quaternion2": {"W": 1.0, "X": 0.0, "Y": 0.0, "Z": 0.0}}, {"number": 22, "position": {"X": 3297.281, "Y": 5170.451, "Z": 232.452, "_padding": 0}, "quaternion": {"W": -0.2866416012751262, "X": 0.0, "Y": 0.0, "Z": 0.9580378867343564}, "rndchk": false, "rndchks": false, "chs": 1.0, "position2": {"X": 0.0, "Y": 0.0, "Z": 0.0, "_padding": 0}, "quaternion2": {"W": 1.0, "X": 0.0, "Y": 0.0, "Z": 0.0}}, {"number": 23, "position": {"X": 3456.238, "Y": 5003.894, "Z": 306.404, "_padding": 0}, "quaternion": {"W": -0.8919041072664031, "X": 0.0, "Y": 0.0, "Z": 0.4522245719123636}, "rndchk": false, "rndchks": false, "chs": 2.0, "position2": {"X": 0.0, "Y": 0.0, "Z": 0.0, "_padding": 0}, "quaternion2": {"W": 1.0, "X": 0.0, "Y": 0.0, "Z": 0.0}}, {"number": 24, "position": {"X": 3559.727, "Y": 5072.618, "Z": 305.206, "_padding": 0}, "quaternion": {"W": -0.8754603095322803, "X": 0.0, "Y": 0.0, "Z": 0.4832900231058406}, "rndchk": false, "rndchks": false, "chs": 1.0, "position2": {"X": 0.0, "Y": 0.0, "Z": 0.0, "_padding": 0}, "quaternion2": {"W": 1.0, "X": 0.0, "Y": 0.0, "Z": 0.0}}, {"number": 25, "position": {"X": 3692.168, "Y": 5180.657, "Z": 293.873, "_padding": 0}, "quaternion": {"W": -0.9953324121402912, "X": 0.0, "Y": 0.0, "Z": 0.09650590315099578}, "rndchk": false, "rndchks": false, "chs": 1.0, "position2": {"X": 0.0, "Y": 0.0, "Z": 0.0, "_padding": 0}, "quaternion2": {"W": 1.0, "X": 0.0, "Y": 0.0, "Z": 0.0}}, {"number": 26, "position": {"X": 3488.252, "Y": 5515.067, "Z": 161.106, "_padding": 0}, "quaternion": {"W": 0.9534489093435614, "X": 0.0, "Y": 0.0, "Z": 0.30155460081314184}, "rndchk": false, "rndchks": false, "chs": 1.0, "position2": {"X": 0.0, "Y": 0.0, "Z": 0.0, "_padding": 0}, "quaternion2": {"W": 1.0, "X": 0.0, "Y": 0.0, "Z": 0.0}}, {"number": 27, "position": {"X": 3397.288, "Y": 5652.225, "Z": 237.209, "_padding": 0}, "quaternion": {"W": 0.963674749763217, "X": 0.0, "Y": 0.0, "Z": 0.26707859642584814}, "rndchk": true, "rndchks": false, "chs": 1.0, "position2": {"X": 0.0, "Y": 0.0, "Z": 0.0, "_padding": 0}, "quaternion2": {"W": 1.0, "X": 0.0, "Y": 0.0, "Z": 0.0}}, {"number": 28, "position": {"X": 3287.52, "Y": 5815.433, "Z": 329.101, "_padding": 0}, "quaternion": {"W": 0.9497018590354757, "X": 0.0, "Y": 0.0, "Z": 0.3131555187834975}, "rndchk": true, "rndchks": false, "chs": 1.0, "position2": {"X": 0.0, "Y": 0.0, "Z": 0.0, "_padding": 0}, "quaternion2": {"W": 1.0, "X": 0.0, "Y": 0.0, "Z": 0.0}}, {"number": 29, "position": {"X": 3160.234, "Y": 6005.134, "Z": 435.823, "_padding": 0}, "quaternion": {"W": 0.9449917367845012, "X": 0.0, "Y": 0.0, "Z": 0.3270942026527099}, "rndchk": true, "rndchks": false, "chs": 1.0, "position2": {"X": 0.0, "Y": 0.0, "Z": 0.0, "_padding": 0}, "quaternion2": {"W": 1.0, "X": 0.0, "Y": 0.0, "Z": 0.0}}, {"number": 30, "position": {"X": 2825.632, "Y": 6484.893, "Z": 862.248, "_padding": 0}, "quaternion": {"W": 0.9546673293168011, "X": 0.0, "Y": 0.0, "Z": 0.2976748063493557}, "rndchk": false, "rndchks": false, "chs": 1.0, "position2": {"X": 0.0, "Y": 0.0, "Z": 0.0, "_padding": 0}, "quaternion2": {"W": 1.0, "X": 0.0, "Y": 0.0, "Z": 0.0}}, {"number": 31, "position": {"X": 2524.562, "Y": 6892.143, "Z": 980.291, "_padding": 0}, "quaternion": {"W": 0.9536224341726748, "X": 0.0, "Y": 0.0, "Z": 0.30100540367671574}, "rndchk": false, "rndchks": false, "chs": 1.0, "position2": {"X": 0.0, "Y": 0.0, "Z": 0.0, "_padding": 0}, "quaternion2": {"W": 1.0, "X": 0.0, "Y": 0.0, "Z": 0.0}}, {"number": 32, "position": {"X": 2434.43, "Y": 6999.453, "Z": 980.297, "_padding": 0}, "quaternion": {"W": 0.8542955762271113, "X": 0.0, "Y": 0.0, "Z": 0.5197875223962075}, "rndchk": false, "rndchks": false, "chs": 1.0, "position2": {"X": 0.0, "Y": 0.0, "Z": 0.0, "_padding": 0}, "quaternion2": {"W": 1.0, "X": 0.0, "Y": 0.0, "Z": 0.0}}, {"number": 33, "position": {"X": 2014.32, "Y": 6749.758, "Z": 1078.117, "_padding": 0}, "quaternion": {"W": 0.48910845896132754, "X": 0.0, "Y": 0.0, "Z": 0.8722229734262194}, "rndchk": false, "rndchks": false, "chs": 1.0, "position2": {"X": 0.0, "Y": 0.0, "Z": 0.0, "_padding": 0}, "quaternion2": {"W": 1.0, "X": 0.0, "Y": 0.0, "Z": 0.0}}, {"number": 34, "position": {"X": 1877.243, "Y": 6709.784, "Z": 1078.094, "_padding": 0}, "quaternion": {"W": 0.8036699518618409, "X": 0.0, "Y": 0.0, "Z": 0.5950752964746447}, "rndchk": false, "rndchks": false, "chs": 1.0, "position2": {"X": 0.0, "Y": 0.0, "Z": 0.0, "_padding": 0}, "quaternion2": {"W": 1.0, "X": 0.0, "Y": 0.0, "Z": 0.0}}, {"number": 35, "position": {"X": 1780.448, "Y": 6775.208, "Z": 1078.069, "_padding": 0}, "quaternion": {"W": 0.90169673816228, "X": 0.0, "Y": 0.0, "Z": 0.43236904651871727}, "rndchk": false, "rndchks": false, "chs": 1.0, "position2": {"X": 0.0, "Y": 0.0, "Z": 0.0, "_padding": 0}, "quaternion2": {"W": 1.0, "X": 0.0, "Y": 0.0, "Z": 0.0}}, {"number": 36, "position": {"X": 1689.515, "Y": 6842.264, "Z": 1078.064, "_padding": 0}, "quaternion": {"W": 0.8933713883278376, "X": 0.0, "Y": 0.0, "Z": 0.4493189986158966}, "rndchk": false, "rndchks": false, "chs": 1.0, "position2": {"X": 0.0, "Y": 0.0, "Z": 0.0, "_padding": 0}, "quaternion2": {"W": 1.0, "X": 0.0, "Y": 0.0, "Z": 0.0}}], "description": null, "lapMode": true, "name": "Stunt - 45\u00b0", "numCheckpoints": 37, "version": "v3.0", "spawn": {"X": 1691.161, "Y": 6836.931, "Z": 1078.064, "_padding": 0}, "dhprops": [], "props": [{"pos": {"X": 2065.602, "Y": 6066.11, "Z": 77.99, "_padding": 0}, "model": -343452421, "speedup": 2}, {"pos": {"X": 2107.224, "Y": 6034.01, "Z": 56.998, "_padding": 0}, "model": 2145085161, "speedup": 4}, {"pos": {"X": 2384.283, "Y": 5750.419, "Z": 53.506, "_padding": 0}, "model": 712522788, "speedup": 1}, {"pos": {"X": 2364.653, "Y": 5780.285, "Z": 44.925, "_padding": 0}, "model": -388593496, "speedup": 5}, {"pos": {"X": 2407.114, "Y": 5715.109, "Z": 82.66, "_padding": 0}, "model": 568446997, "speedup": 1}, {"pos": {"X": 2418.731, "Y": 5697.8, "Z": 97.45, "_padding": 0}, "model": -66244843, "speedup": 5}, {"pos": {"X": 2435.958, "Y": 5671.194, "Z": 119.871, "_padding": 0}, "model": -1151630586, "speedup": 5}, {"pos": {"X": 2518.374, "Y": 5546.793, "Z": 135.634, "_padding": 0}, "model": 1333144381, "speedup": 1}, {"pos": {"X": 2564.942, "Y": 5476.431, "Z": 135.644, "_padding": 0}, "model": 1333144381, "speedup": 1}, {"pos": {"X": 2584.116, "Y": 5446.956, "Z": 135.745, "_padding": 0}, "model": 600369530, "speedup": 1}, {"pos": {"X": 2672.354, "Y": 5314.648, "Z": 135.745, "_padding": 0}, "model": 600369530, "speedup": 1}, {"pos": {"X": 2611.51, "Y": 5406.069, "Z": 135.644, "_padding": 0}, "model": 1333144381, "speedup": 1}, {"pos": {"X": 2709.873, "Y": 5258.609, "Z": 144.223, "_padding": 0}, "model": 712522788, "speedup": 1}, {"pos": {"X": 2692.051, "Y": 5285.001, "Z": 135.75, "_padding": 0}, "model": -388593496, "speedup": 5}, {"pos": {"X": 2722.317, "Y": 5240.215, "Z": 159.328, "_padding": 0}, "model": -278438319, "speedup": 5}, {"pos": {"X": 2733.896, "Y": 5222.786, "Z": 173.99, "_padding": 0}, "model": -278438319, "speedup": 5}, {"pos": {"X": 2813.225, "Y": 5105.561, "Z": 179.667, "_padding": 0}, "model": 600369530, "speedup": 3}, {"pos": {"X": 2902.152, "Y": 4973.716, "Z": 179.667, "_padding": 0}, "model": 600369530, "speedup": 3}, {"pos": {"X": 2955.286, "Y": 4894.659, "Z": 187.222, "_padding": 0}, "model": 959371665, "speedup": 3}, {"pos": {"X": 3458.668, "Y": 5560.78, "Z": 186.386, "_padding": 0}, "model": 600369530, "speedup": 2}, {"pos": {"X": 1885.22, "Y": 6196.323, "Z": 153.75, "_padding": 0}, "model": 658306424, "speedup": 2}, {"pos": {"X": 1748.869, "Y": 6295.875, "Z": 251.218, "_padding": 0}, "model": 658306424, "speedup": 2}, {"pos": {"X": 1612.288, "Y": 6395.132, "Z": 348.72, "_padding": 0}, "model": 658306424, "speedup": 2}, {"pos": {"X": 1475.626, "Y": 6494.056, "Z": 446.161, "_padding": 0}, "model": 658306424, "speedup": 2}, {"pos": {"X": 1338.837, "Y": 6593.066, "Z": 543.678, "_padding": 0}, "model": 658306424, "speedup": 2}, {"pos": {"X": 1065.326, "Y": 6791.202, "Z": 738.654, "_padding": 0}, "model": 658306424, "speedup": 2}, {"pos": {"X": 3260.614, "Y": 5856.305, "Z": 336.997, "_padding": 0}, "model": -227156169, "speedup": 5}, {"pos": {"X": 2935.815, "Y": 4923.71, "Z": 179.545, "_padding": 0}, "model": -388593496, "speedup": 5}, {"pos": {"X": 3095.151, "Y": 6100.886, "Z": 473.891, "_padding": 0}, "model": -227156169, "speedup": 2}, {"pos": {"X": 3197.73, "Y": 5950.679, "Z": 391.446, "_padding": 0}, "model": -227156169, "speedup": 2}, {"pos": {"X": 3034.116, "Y": 6196.894, "Z": 528.347, "_padding": 0}, "model": -227156169, "speedup": 2}, {"pos": {"X": 2992.166, "Y": 4839.266, "Z": 167.367, "_padding": 0}, "model": 1152255454, "speedup": 3}, {"pos": {"X": 3219.381, "Y": 4809.241, "Z": 254.217, "_padding": 0}, "model": 1152255454, "speedup": 5}, {"pos": {"X": 3281.888, "Y": 4850.657, "Z": 254.283, "_padding": 0}, "model": 100090969, "speedup": 5}, {"pos": {"X": 3327.61, "Y": 4909.579, "Z": 240.453, "_padding": 0}, "model": -944087079, "speedup": 5}, {"pos": {"X": 3256.67, "Y": 5067.54, "Z": 182.424, "_padding": 0}, "model": 1152255454, "speedup": 5}, {"pos": {"X": 3282.652, "Y": 5028.128, "Z": 233.747, "_padding": 0}, "model": 142505733, "speedup": 5}, {"pos": {"X": 3356.318, "Y": 5079.792, "Z": 239.26, "_padding": 0}, "model": 142505733, "speedup": 5}, {"pos": {"X": 3386.437, "Y": 5033.451, "Z": 212.644, "_padding": 0}, "model": 100090969, "speedup": 5}, {"pos": {"X": 928.545, "Y": 6890.248, "Z": 836.131, "_padding": 0}, "model": 658306424, "speedup": 2}, {"pos": {"X": 791.795, "Y": 6989.283, "Z": 933.705, "_padding": 0}, "model": 658306424, "speedup": 2}, {"pos": {"X": 655.061, "Y": 7088.179, "Z": 1031.232, "_padding": 0}, "model": 658306424, "speedup": 2}, {"pos": {"X": 565.634, "Y": 7152.813, "Z": 1095.1, "_padding": 0}, "model": 100090969, "speedup": 2}, {"pos": {"X": 683.113, "Y": 7459.923, "Z": 1144.078, "_padding": 0}, "model": 1969602791, "speedup": 2}, {"pos": {"X": 809.74, "Y": 7489.168, "Z": 1094.736, "_padding": 0}, "model": 100090969, "speedup": 2}, {"pos": {"X": 862.323, "Y": 7451.13, "Z": 1057.19, "_padding": 0}, "model": 1152255454, "speedup": 2}, {"pos": {"X": 977.902, "Y": 7366.734, "Z": 1077.905, "_padding": 0}, "model": -780495775, "speedup": 2}, {"pos": {"X": 909.026, "Y": 7417.335, "Z": 1083.46, "_padding": 0}, "model": 959371665, "speedup": 2}, {"pos": {"X": 1105.906, "Y": 7272.361, "Z": 1077.915, "_padding": 0}, "model": -780495775, "speedup": 2}, {"pos": {"X": 933.474, "Y": 7399.542, "Z": 1077.799, "_padding": 0}, "model": -388593496, "speedup": 5}, {"pos": {"X": 858.646, "Y": 7453.772, "Z": 1117.325, "_padding": 0}, "model": -66244843, "speedup": 5}, {"pos": {"X": 3027.991, "Y": 4785.147, "Z": 204.912, "_padding": 0}, "model": 100090969, "speedup": 3}, {"pos": {"X": 3084.824, "Y": 4749.299, "Z": 240.236, "_padding": 0}, "model": -944087079, "speedup": 3}, {"pos": {"X": 3156.844, "Y": 4767.892, "Z": 254.283, "_padding": 0}, "model": 100090969, "speedup": 5}, {"pos": {"X": 3317.342, "Y": 4975.852, "Z": 205.326, "_padding": 0}, "model": 100090969, "speedup": 5}, {"pos": {"X": 3215.322, "Y": 5130.062, "Z": 182.49, "_padding": 0}, "model": 100090969, "speedup": 5}, {"pos": {"X": 3214.442, "Y": 5213.02, "Z": 190.077, "_padding": 0}, "model": 234083239, "speedup": 5}, {"pos": {"X": 3290.393, "Y": 5179.777, "Z": 182.477, "_padding": 0}, "model": 100090969, "speedup": 5}, {"pos": {"X": 3331.745, "Y": 5117.255, "Z": 182.402, "_padding": 0}, "model": 1152255454, "speedup": 5}, {"pos": {"X": 3442.698, "Y": 4996.714, "Z": 247.979, "_padding": 0}, "model": -944087079, "speedup": 5}, {"pos": {"X": 3515.003, "Y": 5014.173, "Z": 262.026, "_padding": 0}, "model": 100090969, "speedup": 5}, {"pos": {"X": 3578.182, "Y": 5054.515, "Z": 261.97, "_padding": 0}, "model": 1817257498, "speedup": 5}, {"pos": {"X": 3641.342, "Y": 5094.943, "Z": 262.026, "_padding": 0}, "model": 100090969, "speedup": 5}, {"pos": {"X": 3688.044, "Y": 5153.176, "Z": 248.195, "_padding": 0}, "model": -944087079, "speedup": 5}, {"pos": {"X": 3678.819, "Y": 5219.583, "Z": 213.078, "_padding": 0}, "model": 1969602791, "speedup": 5}, {"pos": {"X": 3410.41, "Y": 5633.781, "Z": 238.947, "_padding": 0}, "model": 1124049486, "speedup": 2}, {"pos": {"X": 3392.076, "Y": 5660.988, "Z": 254.271, "_padding": 0}, "model": -1170462683, "speedup": 5}, {"pos": {"X": 3373.741, "Y": 5688.196, "Z": 269.595, "_padding": 0}, "model": 1124049486, "speedup": 2}, {"pos": {"X": 3355.407, "Y": 5715.403, "Z": 284.919, "_padding": 0}, "model": -1170462683, "speedup": 5}, {"pos": {"X": 3337.073, "Y": 5742.611, "Z": 300.243, "_padding": 0}, "model": 1124049486, "speedup": 5}, {"pos": {"X": 3318.738, "Y": 5769.818, "Z": 315.567, "_padding": 0}, "model": -1170462683, "speedup": 5}, {"pos": {"X": 3300.404, "Y": 5797.026, "Z": 330.891, "_padding": 0}, "model": 1124049486, "speedup": 5}, {"pos": {"X": 3282.069, "Y": 5824.233, "Z": 346.215, "_padding": 0}, "model": -1170462683, "speedup": 5}, {"pos": {"X": 3268.134, "Y": 5844.865, "Z": 357.844, "_padding": 0}, "model": 1688773919, "speedup": 5}, {"pos": {"X": 3254.261, "Y": 5865.499, "Z": 369.461, "_padding": 0}, "model": -1170462683, "speedup": 5}, {"pos": {"X": 3235.927, "Y": 5892.707, "Z": 384.785, "_padding": 0}, "model": -46524906, "speedup": 5}, {"pos": {"X": 3217.593, "Y": 5919.914, "Z": 400.109, "_padding": 0}, "model": -1170462683, "speedup": 5}, {"pos": {"X": 3203.66, "Y": 5940.543, "Z": 411.745, "_padding": 0}, "model": 1688773919, "speedup": 5}, {"pos": {"X": 3189.785, "Y": 5961.179, "Z": 423.355, "_padding": 0}, "model": -1170462683, "speedup": 5}, {"pos": {"X": 3171.451, "Y": 5988.386, "Z": 438.679, "_padding": 0}, "model": 1124049486, "speedup": 5}, {"pos": {"X": 3153.116, "Y": 6015.594, "Z": 454.003, "_padding": 0}, "model": -1170462683, "speedup": 5}, {"pos": {"X": 3134.782, "Y": 6042.801, "Z": 469.327, "_padding": 0}, "model": 1124049486, "speedup": 5}, {"pos": {"X": 3116.447, "Y": 6070.009, "Z": 484.651, "_padding": 0}, "model": -1170462683, "speedup": 5}, {"pos": {"X": 3088.64, "Y": 6111.274, "Z": 507.898, "_padding": 0}, "model": -1170462683, "speedup": 5}, {"pos": {"X": 3070.305, "Y": 6138.482, "Z": 523.222, "_padding": 0}, "model": -46524906, "speedup": 5}, {"pos": {"X": 3051.971, "Y": 6165.689, "Z": 538.546, "_padding": 0}, "model": -1170462683, "speedup": 5}, {"pos": {"X": 3024.163, "Y": 6206.955, "Z": 561.782, "_padding": 0}, "model": -1170462683, "speedup": 5}, {"pos": {"X": 3337.469, "Y": 5108.417, "Z": 232.246, "_padding": 0}, "model": -66244843, "speedup": 5}, {"pos": {"X": 2846.237, "Y": 6457.437, "Z": 852.816, "_padding": 0}, "model": 953286133, "speedup": 3}, {"pos": {"X": 1233.91, "Y": 7177.989, "Z": 1077.925, "_padding": 0}, "model": -780495775, "speedup": 3}, {"pos": {"X": 2762.614, "Y": 6572.045, "Z": 890.838, "_padding": 0}, "model": 953286133, "speedup": 3}, {"pos": {"X": 1361.914, "Y": 7083.616, "Z": 1077.935, "_padding": 0}, "model": -780495775, "speedup": 2}, {"pos": {"X": 1489.919, "Y": 6989.244, "Z": 1077.945, "_padding": 0}, "model": -780495775, "speedup": 2}, {"pos": {"X": 2752.0, "Y": 6586.447, "Z": 895.746, "_padding": 0}, "model": 600369530, "speedup": 2}, {"pos": {"X": 2710.961, "Y": 6642.856, "Z": 923.255, "_padding": 0}, "model": 712522788, "speedup": 2}, {"pos": {"X": 2588.71, "Y": 6803.281, "Z": 980.082, "_padding": 0}, "model": 953286133, "speedup": 3}, {"pos": {"X": 2420.815, "Y": 6985.911, "Z": 980.234, "_padding": 0}, "model": 778004626, "speedup": 3}, {"pos": {"X": 2842.292, "Y": 6462.171, "Z": 854.595, "_padding": 0}, "model": 600369530, "speedup": 3}, {"pos": {"X": 2879.473, "Y": 6411.113, "Z": 837.643, "_padding": 0}, "model": -388593496, "speedup": 5}, {"pos": {"X": 2818.234, "Y": 6495.275, "Z": 865.482, "_padding": 0}, "model": -388593496, "speedup": 5}, {"pos": {"X": 2736.478, "Y": 6607.831, "Z": 902.718, "_padding": 0}, "model": -388593496, "speedup": 5}, {"pos": {"X": 2700.604, "Y": 6657.058, "Z": 943.73, "_padding": 0}, "model": -278438319, "speedup": 5}, {"pos": {"X": 2302.931, "Y": 6943.339, "Z": 980.178, "_padding": 0}, "model": -780495775, "speedup": 5}, {"pos": {"X": 2263.571, "Y": 6915.596, "Z": 988.694, "_padding": 0}, "model": -1765141602, "speedup": 5}, {"pos": {"X": 2244.893, "Y": 6902.678, "Z": 1004.358, "_padding": 0}, "model": -278438319, "speedup": 5}, {"pos": {"X": 2227.872, "Y": 6890.917, "Z": 1019.276, "_padding": 0}, "model": -278438319, "speedup": 5}, {"pos": {"X": 2289.895, "Y": 6933.938, "Z": 980.062, "_padding": 0}, "model": -388593496, "speedup": 5}, {"pos": {"X": 2210.832, "Y": 6879.132, "Z": 1034.228, "_padding": 0}, "model": -278438319, "speedup": 5}, {"pos": {"X": 2236.816, "Y": 6897.142, "Z": 1011.696, "_padding": 0}, "model": -1006978322, "speedup": 5}, {"pos": {"X": 2193.955, "Y": 6867.461, "Z": 1049.037, "_padding": 0}, "model": -278438319, "speedup": 5}, {"pos": {"X": 2202.515, "Y": 6873.451, "Z": 1041.797, "_padding": 0}, "model": -1006978322, "speedup": 5}, {"pos": {"X": 2502.535, "Y": 6922.639, "Z": 980.243, "_padding": 0}, "model": -8801519, "speedup": 5}, {"pos": {"X": 1202.09, "Y": 6692.165, "Z": 641.183, "_padding": 0}, "model": 658306424, "speedup": 5}, {"pos": {"X": 1617.923, "Y": 6894.872, "Z": 1077.955, "_padding": 0}, "model": -780495775, "speedup": 5}, {"pos": {"X": 1724.593, "Y": 6816.228, "Z": 1078.01, "_padding": 0}, "model": -248283675, "speedup": 5}, {"pos": {"X": 1809.93, "Y": 6753.313, "Z": 1078.02, "_padding": 0}, "model": 711357200, "speedup": 5}, {"pos": {"X": 1876.065, "Y": 6711.035, "Z": 1078.03, "_padding": 0}, "model": 1682688844, "speedup": 5}, {"pos": {"X": 1921.485, "Y": 6707.313, "Z": 1078.037, "_padding": 0}, "model": 1682688844, "speedup": 5}, {"pos": {"X": 1965.388, "Y": 6723.505, "Z": 1078.043, "_padding": 0}, "model": -948305930, "speedup": 5}, {"pos": {"X": 2010.957, "Y": 6748.402, "Z": 1078.053, "_padding": 0}, "model": -948305930, "speedup": 5}, {"pos": {"X": 2061.106, "Y": 6777.5, "Z": 1077.908, "_padding": 0}, "model": 110106994, "speedup": 5}, {"pos": {"X": 806.917, "Y": 6978.427, "Z": 962.339, "_padding": 0}, "model": -227156169, "speedup": 3}, {"pos": {"X": 1365.06, "Y": 6573.476, "Z": 564.696, "_padding": 0}, "model": -227156169, "speedup": 3}, {"pos": {"X": 827.08, "Y": 6967.848, "Z": 965.4, "_padding": 0}, "model": 1515979145, "speedup": 1}, {"pos": {"X": 1381.795, "Y": 6557.979, "Z": 567.48, "_padding": 0}, "model": 1515979145, "speedup": 1}, {"pos": {"X": 3614.207, "Y": 5320.46, "Z": 201.409, "_padding": 0}, "model": 600369530, "speedup": 5}, {"pos": {"X": 3552.391, "Y": 5417.111, "Z": 135.226, "_padding": 0}, "model": -8801519, "speedup": 5}, {"pos": {"X": 3534.513, "Y": 5056.29, "Z": 305.249, "_padding": 0}, "model": -227275508, "speedup": 1}, {"pos": {"X": 1382.789, "Y": 6556.789, "Z": 570.381, "_padding": 0}, "model": -1006978322, "speedup": 1}, {"pos": {"X": 826.995, "Y": 6967.54, "Z": 968.921, "_padding": 0}, "model": -1006978322, "speedup": 1}, {"pos": {"X": 1330.537, "Y": 7106.699, "Z": 1077.849, "_padding": 0}, "model": -388593496, "speedup": 5}, {"pos": {"X": 2949.293, "Y": 6321.205, "Z": 731.508, "_padding": 0}, "model": -1170462683, "speedup": 5}, {"pos": {"X": 2942.573, "Y": 6331.602, "Z": 765.543, "_padding": 0}, "model": 1124049486, "speedup": 5}, {"pos": {"X": 2976.831, "Y": 6278.469, "Z": 633.793, "_padding": 0}, "model": -1170462683, "speedup": 5}, {"pos": {"X": 3038.067, "Y": 6186.322, "Z": 550.159, "_padding": 0}, "model": 894554243, "speedup": 5}, {"pos": {"X": 2928.449, "Y": 5996.441, "Z": 306.276, "_padding": 0}, "model": 1124049486, "speedup": 5}, {"pos": {"X": 3102.543, "Y": 6090.642, "Z": 496.275, "_padding": 0}, "model": 894554243, "speedup": 5}, {"pos": {"X": 2997.854, "Y": 6246.496, "Z": 596.47, "_padding": 0}, "model": 2138176025, "speedup": 3}, {"pos": {"X": 2962.664, "Y": 6300.466, "Z": 680.558, "_padding": 0}, "model": 1533556199, "speedup": 5}, {"pos": {"X": 3524.272, "Y": 5460.146, "Z": 130.429, "_padding": 0}, "model": -8801519, "speedup": 2}, {"pos": {"X": 3422.469, "Y": 5615.789, "Z": 217.219, "_padding": 0}, "model": -1006978322, "speedup": 5}, {"pos": {"X": 3477.766, "Y": 5531.472, "Z": 169.962, "_padding": 0}, "model": -388593496, "speedup": 5}, {"pos": {"X": 3541.516, "Y": 5434.101, "Z": 136.83, "_padding": 0}, "model": 712522788, "speedup": 2}, {"pos": {"X": 763.909, "Y": 7485.6, "Z": 1172.565, "_padding": 0}, "model": -2019132063, "speedup": 2}, {"pos": {"X": 555.55, "Y": 7197.172, "Z": 1172.429, "_padding": 0}, "model": -2019132063, "speedup": 2}, {"pos": {"X": 662.611, "Y": 7082.583, "Z": 1083.505, "_padding": 0}, "model": -780495775, "speedup": 2}, {"pos": {"X": 639.215, "Y": 7356.551, "Z": 1187.168, "_padding": 0}, "model": -780495775, "speedup": 2}, {"pos": {"X": 554.935, "Y": 7282.372, "Z": 1143.958, "_padding": 0}, "model": 1969602791, "speedup": 2}, {"pos": {"X": 2691.092, "Y": 6670.189, "Z": 963.27, "_padding": 0}, "model": -278438319, "speedup": 5}, {"pos": {"X": 2707.293, "Y": 6647.764, "Z": 929.938, "_padding": 0}, "model": -66244843, "speedup": 4}]}