{"checkpoints": [{"number": 0, "position": {"X": -983.434, "Y": -126.519, "Z": 98.219, "_padding": 0}, "quaternion": {"W": 0.9635207637039144, "X": 0.0, "Y": 0.0, "Z": 0.26763358890734484}, "cpbs1": 1, "chs": 1.0, "position2": {"X": 0.0, "Y": 0.0, "Z": 0.0, "_padding": 0}, "quaternion2": {"W": 1.0, "X": 0.0, "Y": 0.0, "Z": 0.0}, "chs2": 1.0}, {"number": 1, "position": {"X": -1075.53, "Y": 32.616, "Z": 98.219, "_padding": 0}, "quaternion": {"W": 0.966270534414392, "X": 0.0, "Y": 0.0, "Z": 0.25752913295882707}, "cpbs1": 1, "chs": 1.0, "position2": {"X": 0.0, "Y": 0.0, "Z": 0.0, "_padding": 0}, "quaternion2": {"W": 1.0, "X": 0.0, "Y": 0.0, "Z": 0.0}, "chs2": 1.0}, {"number": 2, "position": {"X": -1172.303, "Y": 201.084, "Z": 98.212, "_padding": 0}, "quaternion": {"W": 0.9844311700883799, "X": 0.0, "Y": 0.0, "Z": 0.1757705076468271}, "cpbs1": 1, "chs": 1.0, "position2": {"X": 0.0, "Y": 0.0, "Z": 0.0, "_padding": 0}, "quaternion2": {"W": 1.0, "X": 0.0, "Y": 0.0, "Z": 0.0}, "chs2": 1.0}, {"number": 3, "position": {"X": -1125.157, "Y": 311.28, "Z": 98.271, "_padding": 0}, "quaternion": {"W": 0.8714150831746447, "X": 0.0, "Y": 0.0, "Z": -0.4905463819209424}, "cpbs1": 1, "chs": 1.0, "position2": {"X": 0.0, "Y": 0.0, "Z": 0.0, "_padding": 0}, "quaternion2": {"W": 1.0, "X": 0.0, "Y": 0.0, "Z": 0.0}, "chs2": 1.0}, {"number": 4, "position": {"X": -992.969, "Y": 281.563, "Z": 98.291, "_padding": 0}, "quaternion": {"W": 0.2541546503947776, "X": 0.0, "Y": 0.0, "Z": -0.9671635919960534}, "cpbs1": 1, "chs": 1.0, "position2": {"X": 0.0, "Y": 0.0, "Z": 0.0, "_padding": 0}, "quaternion2": {"W": 1.0, "X": 0.0, "Y": 0.0, "Z": 0.0}, "chs2": 1.0}, {"number": 5, "position": {"X": -906.688, "Y": 131.688, "Z": 98.311, "_padding": 0}, "quaternion": {"W": 0.2538254719944952, "X": 0.0, "Y": 0.0, "Z": -0.967250034772174}, "cpbs1": 3, "chs": 1.0, "position2": {"X": 0.0, "Y": 0.0, "Z": 0.0, "_padding": 0}, "quaternion2": {"W": 1.0, "X": 0.0, "Y": 0.0, "Z": 0.0}, "chs2": 1.0}, {"number": 6, "position": {"X": -761.681, "Y": -122.293, "Z": 36.866, "_padding": 0}, "quaternion": {"W": -0.24823342550744293, "X": 0.0, "Y": 0.0, "Z": 0.9687002459279345}, "cpbs1": 1, "chs": 1.0, "position2": {"X": 0.0, "Y": 0.0, "Z": 0.0, "_padding": 0}, "quaternion2": {"W": 1.0, "X": 0.0, "Y": 0.0, "Z": 0.0}, "chs2": 1.0}, {"number": 7, "position": {"X": -642.269, "Y": -330.434, "Z": 33.811, "_padding": 0}, "quaternion": {"W": 0.25720025830561094, "X": 0.0, "Y": 0.0, "Z": -0.9663581257109225}, "cpbs1": 134217731, "chs": 1.0, "position2": {"X": 0.0, "Y": 0.0, "Z": 0.0, "_padding": 0}, "quaternion2": {"W": 1.0, "X": 0.0, "Y": 0.0, "Z": 0.0}, "chs2": 1.0}, {"number": 8, "position": {"X": -671.677, "Y": -367.248, "Z": 33.606, "_padding": 0}, "quaternion": {"W": 0.8780163922844564, "X": 0.0, "Y": 0.0, "Z": -0.4786305619993228}, "cpbs1": 1, "chs": 1.0, "position2": {"X": 0.0, "Y": 0.0, "Z": 0.0, "_padding": 0}, "quaternion2": {"W": 1.0, "X": 0.0, "Y": 0.0, "Z": 0.0}, "chs2": 1.0}, {"number": 9, "position": {"X": -559.345, "Y": -296.936, "Z": 34.184, "_padding": 0}, "quaternion": {"W": -0.8537644188125486, "X": 0.0, "Y": 0.0, "Z": 0.5206595021409588}, "cpbs1": 1, "chs": 1.0, "position2": {"X": 0.0, "Y": 0.0, "Z": 0.0, "_padding": 0}, "quaternion2": {"W": 1.0, "X": 0.0, "Y": 0.0, "Z": 0.0}, "chs2": 1.0}, {"number": 10, "position": {"X": -443.205, "Y": -260.175, "Z": 34.793, "_padding": 0}, "quaternion": {"W": 0.25213691647368763, "X": 0.0, "Y": 0.0, "Z": -0.967691570362758}, "cpbs1": 1, "chs": 1.0, "position2": {"X": 0.0, "Y": 0.0, "Z": 0.0, "_padding": 0}, "quaternion2": {"W": 1.0, "X": 0.0, "Y": 0.0, "Z": 0.0}, "chs2": 1.0}, {"number": 11, "position": {"X": -417.717, "Y": -296.944, "Z": 33.951, "_padding": 0}, "quaternion": {"W": -0.1200675310047771, "X": 0.0, "Y": 0.0, "Z": -0.9927657266437117}, "cpbs1": 1, "chs": 1.0, "position2": {"X": 0.0, "Y": 0.0, "Z": 0.0, "_padding": 0}, "quaternion2": {"W": 1.0, "X": 0.0, "Y": 0.0, "Z": 0.0}, "chs2": 1.0}, {"number": 12, "position": {"X": -426.641, "Y": -373.274, "Z": 31.837, "_padding": 0}, "quaternion": {"W": 0.6388215301809115, "X": 0.0, "Y": 0.0, "Z": -0.7693549587656655}, "cpbs1": 1, "chs": 1.0, "position2": {"X": 0.0, "Y": 0.0, "Z": 0.0, "_padding": 0}, "quaternion2": {"W": 1.0, "X": 0.0, "Y": 0.0, "Z": 0.0}, "chs2": 1.0}, {"number": 13, "position": {"X": -230.213, "Y": -425.25, "Z": 29.786, "_padding": 0}, "quaternion": {"W": 0.41793049861862497, "X": 0.0, "Y": 0.0, "Z": -0.9084790026876722}, "cpbs1": 1, "chs": 1.0, "position2": {"X": 0.0, "Y": 0.0, "Z": 0.0, "_padding": 0}, "quaternion2": {"W": 1.0, "X": 0.0, "Y": 0.0, "Z": 0.0}, "chs2": 1.0}, {"number": 14, "position": {"X": -178.39, "Y": -487.653, "Z": 33.455, "_padding": 0}, "quaternion": {"W": -0.5671755186669372, "X": 0.0, "Y": 0.0, "Z": 0.8235969469497145}, "cpbs1": 67108865, "chs": 1.0, "position2": {"X": 0.0, "Y": 0.0, "Z": 0.0, "_padding": 0}, "quaternion2": {"W": 1.0, "X": 0.0, "Y": 0.0, "Z": 0.0}, "chs2": 1.0}, {"number": 15, "position": {"X": -73.263, "Y": -523.169, "Z": 30.771, "_padding": 0}, "quaternion": {"W": -0.7074337510932163, "X": 0.0, "Y": 0.0, "Z": 0.7067796600173079}, "cpbs1": 1, "chs": 1.0, "position2": {"X": 0.0, "Y": 0.0, "Z": 0.0, "_padding": 0}, "quaternion2": {"W": 1.0, "X": 0.0, "Y": 0.0, "Z": 0.0}, "chs2": 1.0}, {"number": 16, "position": {"X": 71.711, "Y": -542.189, "Z": 32.838, "_padding": 0}, "quaternion": {"W": -0.6514696626449435, "X": 0.0, "Y": 0.0, "Z": 0.758674685654717}, "cpbs1": 1, "chs": 1.0, "position2": {"X": 0.0, "Y": 0.0, "Z": 0.0, "_padding": 0}, "quaternion2": {"W": 1.0, "X": 0.0, "Y": 0.0, "Z": 0.0}, "chs2": 1.0}, {"number": 17, "position": {"X": 295.271, "Y": -547.214, "Z": 42.287, "_padding": 0}, "quaternion": {"W": -0.6746631844089336, "X": 0.0, "Y": 0.0, "Z": 0.7381257261491414}, "cpbs1": 134217731, "chs": 1.0, "position2": {"X": 0.0, "Y": 0.0, "Z": 0.0, "_padding": 0}, "quaternion2": {"W": 1.0, "X": 0.0, "Y": 0.0, "Z": 0.0}, "chs2": 1.0}, {"number": 18, "position": {"X": 230.424, "Y": -676.513, "Z": 36.416, "_padding": 0}, "quaternion": {"W": -0.9832310445656145, "X": 0.0, "Y": 0.0, "Z": 0.18236423169692706}, "cpbs1": 67108865, "chs": 0.3, "position2": {"X": 0.0, "Y": 0.0, "Z": 0.0, "_padding": 0}, "quaternion2": {"W": 1.0, "X": 0.0, "Y": 0.0, "Z": 0.0}, "chs2": 1.0}, {"number": 19, "position": {"X": 302.203, "Y": -449.794, "Z": 42.578, "_padding": 0}, "quaternion": {"W": -0.998490535700707, "X": 0.0, "Y": 0.0, "Z": -0.054924039510173904}, "cpbs1": 1, "chs": 1.1, "position2": {"X": 0.0, "Y": 0.0, "Z": 0.0, "_padding": 0}, "quaternion2": {"W": 1.0, "X": 0.0, "Y": 0.0, "Z": 0.0}, "chs2": 1.0}, {"number": 20, "position": {"X": 275.412, "Y": -371.191, "Z": 44.059, "_padding": 0}, "quaternion": {"W": -0.8243880702891975, "X": 0.0, "Y": 0.0, "Z": -0.566025007897048}, "cpbs1": 1, "chs": 1.4, "position2": {"X": 0.0, "Y": 0.0, "Z": 0.0, "_padding": 0}, "quaternion2": {"W": 1.0, "X": 0.0, "Y": 0.0, "Z": 0.0}, "chs2": 1.0}, {"number": 21, "position": {"X": 90.517, "Y": -304.534, "Z": 66.488, "_padding": 0}, "quaternion": {"W": -0.8113342823207298, "X": 0.0, "Y": 0.0, "Z": -0.5845824854809681}, "cpbs1": 515, "chs": 1.0, "position2": {"X": 0.0, "Y": 0.0, "Z": 0.0, "_padding": 0}, "quaternion2": {"W": 1.0, "X": 0.0, "Y": 0.0, "Z": 0.0}, "chs2": 1.0}, {"number": 22, "position": {"X": -142.442, "Y": -128.221, "Z": 116.76, "_padding": 0}, "quaternion": {"W": 0.9211888012777092, "X": 0.0, "Y": 0.0, "Z": 0.38911591126621536}, "cpbs1": 515, "chs": 1.0, "position2": {"X": 0.0, "Y": 0.0, "Z": 0.0, "_padding": 0}, "quaternion2": {"W": 1.0, "X": 0.0, "Y": 0.0, "Z": 0.0}, "chs2": 1.0}, {"number": 23, "position": {"X": -323.741, "Y": -20.382, "Z": 77.819, "_padding": 0}, "quaternion": {"W": 0.8007365983852894, "X": 0.0, "Y": 0.0, "Z": 0.5990166107933533}, "cpbs1": 515, "chs": 1.0, "position2": {"X": 0.0, "Y": 0.0, "Z": 0.0, "_padding": 0}, "quaternion2": {"W": 1.0, "X": 0.0, "Y": 0.0, "Z": 0.0}, "chs2": 1.0}, {"number": 24, "position": {"X": -418.181, "Y": -37.811, "Z": 76.912, "_padding": 0}, "quaternion": {"W": 0.2605129339708523, "X": 0.0, "Y": 0.0, "Z": 0.9654703575117666}, "cpbs1": 515, "chs": 1.0, "position2": {"X": 0.0, "Y": 0.0, "Z": 0.0, "_padding": 0}, "quaternion2": {"W": 1.0, "X": 0.0, "Y": 0.0, "Z": 0.0}, "chs2": 1.0}, {"number": 25, "position": {"X": -477.186, "Y": -144.371, "Z": 72.848, "_padding": 0}, "quaternion": {"W": 0.01920616743700348, "X": 0.0, "Y": 0.0, "Z": 0.9998155445542851}, "cpbs1": 515, "chs": 1.0, "position2": {"X": 0.0, "Y": 0.0, "Z": 0.0, "_padding": 0}, "quaternion2": {"W": 1.0, "X": 0.0, "Y": 0.0, "Z": 0.0}, "chs2": 1.0}, {"number": 26, "position": {"X": -473.692, "Y": -317.898, "Z": 74.364, "_padding": 0}, "quaternion": {"W": 0.061057249901837925, "X": 0.0, "Y": 0.0, "Z": 0.9981342656348516}, "cpbs1": 134218243, "chs": 0.7, "position2": {"X": 0.0, "Y": 0.0, "Z": 0.0, "_padding": 0}, "quaternion2": {"W": 1.0, "X": 0.0, "Y": 0.0, "Z": 0.0}, "chs2": 1.0}, {"number": 27, "position": {"X": -375.377, "Y": -348.819, "Z": 93.919, "_padding": 0}, "quaternion": {"W": -0.6087545056715807, "X": 0.0, "Y": 0.0, "Z": 0.7933586527066743}, "cpbs1": 515, "chs": 1.0, "position2": {"X": 0.0, "Y": 0.0, "Z": 0.0, "_padding": 0}, "quaternion2": {"W": 1.0, "X": 0.0, "Y": 0.0, "Z": 0.0}, "chs2": 1.0}, {"number": 28, "position": {"X": -131.923, "Y": -419.234, "Z": 85.704, "_padding": 0}, "quaternion": {"W": -0.5764251852133735, "X": 0.0, "Y": 0.0, "Z": 0.8171499286249299}, "cpbs1": 3, "chs": 1.0, "position2": {"X": 0.0, "Y": 0.0, "Z": 0.0, "_padding": 0}, "quaternion2": {"W": 1.0, "X": 0.0, "Y": 0.0, "Z": 0.0}, "chs2": 1.0}, {"number": 29, "position": {"X": -54.071, "Y": -453.227, "Z": 85.707, "_padding": 0}, "quaternion": {"W": -0.36973864904847015, "X": 0.0, "Y": 0.0, "Z": 0.9291357981478339}, "cpbs1": 3, "chs": 1.0, "position2": {"X": 0.0, "Y": 0.0, "Z": 0.0, "_padding": 0}, "quaternion2": {"W": 1.0, "X": 0.0, "Y": 0.0, "Z": 0.0}, "chs2": 1.0}, {"number": 30, "position": {"X": -51.798, "Y": -511.021, "Z": 85.837, "_padding": 0}, "quaternion": {"W": 0.1684979814440789, "X": 0.0, "Y": 0.0, "Z": 0.9857019987041067}, "cpbs1": 3, "chs": 1.0, "position2": {"X": 0.0, "Y": 0.0, "Z": 0.0, "_padding": 0}, "quaternion2": {"W": 1.0, "X": 0.0, "Y": 0.0, "Z": 0.0}, "chs2": 1.0}, {"number": 31, "position": {"X": -109.401, "Y": -537.255, "Z": 85.8, "_padding": 0}, "quaternion": {"W": 0.7996898981115544, "X": 0.0, "Y": 0.0, "Z": 0.6004132467378877}, "cpbs1": 3, "chs": 1.0, "position2": {"X": 0.0, "Y": 0.0, "Z": 0.0, "_padding": 0}, "quaternion2": {"W": 1.0, "X": 0.0, "Y": 0.0, "Z": 0.0}, "chs2": 1.0}, {"number": 32, "position": {"X": -191.396, "Y": -497.818, "Z": 85.673, "_padding": 0}, "quaternion": {"W": 0.9438038358294811, "X": 0.0, "Y": 0.0, "Z": 0.33050615648359377}, "cpbs1": 3, "chs": 1.0, "position2": {"X": 0.0, "Y": 0.0, "Z": 0.0, "_padding": 0}, "quaternion2": {"W": 1.0, "X": 0.0, "Y": 0.0, "Z": 0.0}, "chs2": 1.0}, {"number": 33, "position": {"X": -183.648, "Y": -419.244, "Z": 85.693, "_padding": 0}, "quaternion": {"W": 0.9838850379335417, "X": 0.0, "Y": 0.0, "Z": -0.1788022151163496}, "cpbs1": 3, "chs": 1.0, "position2": {"X": 0.0, "Y": 0.0, "Z": 0.0, "_padding": 0}, "quaternion2": {"W": 1.0, "X": 0.0, "Y": 0.0, "Z": 0.0}, "chs2": 1.0}, {"number": 34, "position": {"X": -152.113, "Y": -332.858, "Z": 85.61, "_padding": 0}, "quaternion": {"W": 0.9838834775523962, "X": 0.0, "Y": 0.0, "Z": -0.17881080112622774}, "cpbs1": 1, "chs": 1.0, "position2": {"X": 0.0, "Y": 0.0, "Z": 0.0, "_padding": 0}, "quaternion2": {"W": 1.0, "X": 0.0, "Y": 0.0, "Z": 0.0}, "chs2": 1.0}, {"number": 35, "position": {"X": -94.8, "Y": -153.867, "Z": 85.59, "_padding": 0}, "quaternion": {"W": 0.9997808661938669, "X": 0.0, "Y": 0.0, "Z": 0.020933695150197405}, "cpbs1": 1, "chs": 1.0, "position2": {"X": 0.0, "Y": 0.0, "Z": 0.0, "_padding": 0}, "quaternion2": {"W": 1.0, "X": 0.0, "Y": 0.0, "Z": 0.0}, "chs2": 1.0}, {"number": 36, "position": {"X": -151.711, "Y": -82.367, "Z": 85.591, "_padding": 0}, "quaternion": {"W": 0.7901603609686508, "X": 0.0, "Y": 0.0, "Z": 0.6129001582263554}, "cpbs1": 1, "chs": 1.0, "position2": {"X": 0.0, "Y": 0.0, "Z": 0.0, "_padding": 0}, "quaternion2": {"W": 1.0, "X": 0.0, "Y": 0.0, "Z": 0.0}, "chs2": 1.0}, {"number": 37, "position": {"X": -223.096, "Y": -64.037, "Z": 85.621, "_padding": 0}, "quaternion": {"W": 0.6996695754370617, "X": 0.0, "Y": 0.0, "Z": 0.7144665738911247}, "cpbs1": 1, "chs": 1.0, "position2": {"X": 0.0, "Y": 0.0, "Z": 0.0, "_padding": 0}, "quaternion2": {"W": 1.0, "X": 0.0, "Y": 0.0, "Z": 0.0}, "chs2": 1.0}, {"number": 38, "position": {"X": -298.649, "Y": -80.157, "Z": 85.627, "_padding": 0}, "quaternion": {"W": 0.5254790757798451, "X": 0.0, "Y": 0.0, "Z": 0.8508065237864363}, "cpbs1": 1, "chs": 1.0, "position2": {"X": 0.0, "Y": 0.0, "Z": 0.0, "_padding": 0}, "quaternion2": {"W": 1.0, "X": 0.0, "Y": 0.0, "Z": 0.0}, "chs2": 1.0}, {"number": 39, "position": {"X": -617.853, "Y": -258.982, "Z": 66.163, "_padding": 0}, "quaternion": {"W": 0.5030274888315495, "X": 0.0, "Y": 0.0, "Z": 0.8642704122436596}, "cpbs1": 3, "chs": 1.0, "position2": {"X": 0.0, "Y": 0.0, "Z": 0.0, "_padding": 0}, "quaternion2": {"W": 1.0, "X": 0.0, "Y": 0.0, "Z": 0.0}, "chs2": 1.0}, {"number": 40, "position": {"X": -697.439, "Y": -303.668, "Z": 66.168, "_padding": 0}, "quaternion": {"W": 0.6626200482157375, "X": 0.0, "Y": 0.0, "Z": 0.7489557207890021}, "cpbs1": 1, "chs": 1.0, "position2": {"X": 0.0, "Y": 0.0, "Z": 0.0, "_padding": 0}, "quaternion2": {"W": 1.0, "X": 0.0, "Y": 0.0, "Z": 0.0}, "chs2": 1.0}, {"number": 41, "position": {"X": -751.877, "Y": -270.936, "Z": 66.171, "_padding": 0}, "quaternion": {"W": 0.9799229647700777, "X": 0.0, "Y": 0.0, "Z": -0.19937648586586434}, "cpbs1": 1, "chs": 1.0, "position2": {"X": 0.0, "Y": 0.0, "Z": 0.0, "_padding": 0}, "quaternion2": {"W": 1.0, "X": 0.0, "Y": 0.0, "Z": 0.0}, "chs2": 1.0}, {"number": 42, "position": {"X": -643.618, "Y": -187.373, "Z": 66.165, "_padding": 0}, "quaternion": {"W": 0.7954681925781998, "X": 0.0, "Y": 0.0, "Z": -0.6059953420583132}, "cpbs1": 1, "chs": 1.0, "position2": {"X": 0.0, "Y": 0.0, "Z": 0.0, "_padding": 0}, "quaternion2": {"W": 1.0, "X": 0.0, "Y": 0.0, "Z": 0.0}, "chs2": 1.0}, {"number": 43, "position": {"X": -542.894, "Y": -216.179, "Z": 66.144, "_padding": 0}, "quaternion": {"W": 0.8660210404283329, "X": 0.0, "Y": 0.0, "Z": -0.5000075574783122}, "cpbs1": 1, "chs": 1.0, "position2": {"X": 0.0, "Y": 0.0, "Z": 0.0, "_padding": 0}, "quaternion2": {"W": 1.0, "X": 0.0, "Y": 0.0, "Z": 0.0}, "chs2": 1.0}, {"number": 44, "position": {"X": -510.962, "Y": -150.828, "Z": 66.154, "_padding": 0}, "quaternion": {"W": 0.942644404070665, "X": 0.0, "Y": 0.0, "Z": 0.33379863312221786}, "cpbs1": 1, "chs": 1.0, "position2": {"X": 0.0, "Y": 0.0, "Z": 0.0, "_padding": 0}, "quaternion2": {"W": 1.0, "X": 0.0, "Y": 0.0, "Z": 0.0}, "chs2": 1.0}, {"number": 45, "position": {"X": -591.598, "Y": -76.171, "Z": 66.142, "_padding": 0}, "quaternion": {"W": 0.9806163684619608, "X": 0.0, "Y": 0.0, "Z": 0.19593758675781422}, "cpbs1": 1, "chs": 1.0, "position2": {"X": 0.0, "Y": 0.0, "Z": 0.0, "_padding": 0}, "quaternion2": {"W": 1.0, "X": 0.0, "Y": 0.0, "Z": 0.0}, "chs2": 1.0}, {"number": 46, "position": {"X": -608.568, "Y": 31.965, "Z": 66.136, "_padding": 0}, "quaternion": {"W": 0.9999984921060738, "X": 0.0, "Y": 0.0, "Z": 0.0017366017328634298}, "cpbs1": 134217731, "chs": 1.0, "position2": {"X": 0.0, "Y": 0.0, "Z": 0.0, "_padding": 0}, "quaternion2": {"W": 1.0, "X": 0.0, "Y": 0.0, "Z": 0.0}, "chs2": 1.0}, {"number": 47, "position": {"X": -676.638, "Y": 190.711, "Z": 166.675, "_padding": 0}, "quaternion": {"W": 0.2503884527268927, "X": 0.0, "Y": 0.0, "Z": 0.9681454553635175}, "cpbs1": 515, "chs": 1.0, "position2": {"X": 0.0, "Y": 0.0, "Z": 0.0, "_padding": 0}, "quaternion2": {"W": 1.0, "X": 0.0, "Y": 0.0, "Z": 0.0}, "chs2": 1.0}, {"number": 48, "position": {"X": -831.297, "Y": -80.468, "Z": 98.24, "_padding": 0}, "quaternion": {"W": -0.25032086281342875, "X": 0.0, "Y": 0.0, "Z": -0.9681629334158278}, "cpbs1": 3, "chs": 1.0, "position2": {"X": 0.0, "Y": 0.0, "Z": 0.0, "_padding": 0}, "quaternion2": {"W": 1.0, "X": 0.0, "Y": 0.0, "Z": 0.0}, "chs2": 1.0}, {"number": 49, "position": {"X": -888.351, "Y": -147.585, "Z": 98.234, "_padding": 0}, "quaternion": {"W": 0.506041290953581, "X": 0.0, "Y": 0.0, "Z": 0.8625092531967603}, "cpbs1": 1, "chs": 1.0, "position2": {"X": 0.0, "Y": 0.0, "Z": 0.0, "_padding": 0}, "quaternion2": {"W": 1.0, "X": 0.0, "Y": 0.0, "Z": 0.0}, "chs2": 1.0}, {"number": 50, "position": {"X": -1030.461, "Y": -231.138, "Z": 98.232, "_padding": 0}, "quaternion": {"W": 0.3632593609989134, "X": 0.0, "Y": 0.0, "Z": 0.931688057585081}, "cpbs1": 1, "chs": 1.0, "position2": {"X": 0.0, "Y": 0.0, "Z": 0.0, "_padding": 0}, "quaternion2": {"W": 1.0, "X": 0.0, "Y": 0.0, "Z": 0.0}, "chs2": 1.0}, {"number": 51, "position": {"X": -1041.441, "Y": -326.673, "Z": 98.351, "_padding": 0}, "quaternion": {"W": -0.2672299668059907, "X": 0.0, "Y": 0.0, "Z": 0.9636327852667058}, "cpbs1": 1, "chs": 1.0, "position2": {"X": 0.0, "Y": 0.0, "Z": 0.0, "_padding": 0}, "quaternion2": {"W": 1.0, "X": 0.0, "Y": 0.0, "Z": 0.0}, "chs2": 1.0}, {"number": 52, "position": {"X": -997.528, "Y": -399.229, "Z": 98.238, "_padding": 0}, "quaternion": {"W": -0.4756165326702363, "X": 0.0, "Y": 0.0, "Z": 0.8796527234373472}, "cpbs1": 1, "chs": 1.0, "position2": {"X": 0.0, "Y": 0.0, "Z": 0.0, "_padding": 0}, "quaternion2": {"W": 1.0, "X": 0.0, "Y": 0.0, "Z": 0.0}, "chs2": 1.0}, {"number": 53, "position": {"X": -906.153, "Y": -410.683, "Z": 98.218, "_padding": 0}, "quaternion": {"W": -0.8651470440299631, "X": 0.0, "Y": 0.0, "Z": 0.50151828701077}, "cpbs1": 1, "chs": 1.0, "position2": {"X": 0.0, "Y": 0.0, "Z": 0.0, "_padding": 0}, "quaternion2": {"W": 1.0, "X": 0.0, "Y": 0.0, "Z": 0.0}, "chs2": 1.0}, {"number": 54, "position": {"X": -932.047, "Y": -214.801, "Z": 98.241, "_padding": 0}, "quaternion": {"W": -0.9668055527702389, "X": 0.0, "Y": 0.0, "Z": -0.2555132543188957}, "cpbs1": 1, "chs": 1.0, "position2": {"X": 0.0, "Y": 0.0, "Z": 0.0, "_padding": 0}, "quaternion2": {"W": 1.0, "X": 0.0, "Y": 0.0, "Z": 0.0}, "chs2": 1.0}], "description": null, "lapMode": true, "name": "Transform - The Grotti Circuit", "numCheckpoints": 55, "version": "v3.0", "spawn": {"X": -932.693, "Y": -220.344, "Z": 98.241, "_padding": 0}}