{"checkpoints": [{"number": 0, "position": {"X": 583.245, "Y": -1714.613, "Z": 28.337, "_padding": 0}, "quaternion": {"W": -0.8428142347665164, "X": 0.0, "Y": 0.0, "Z": -0.5382045760442133}, "chs": 1.0}, {"number": 1, "position": {"X": 394.378, "Y": -1565.588, "Z": 28.341, "_padding": 0}, "quaternion": {"W": -0.9031218207028806, "X": 0.0, "Y": 0.0, "Z": -0.42938441631050617}, "chs": 1.0}, {"number": 2, "position": {"X": 172.394, "Y": -1401.002, "Z": 28.34, "_padding": 0}, "quaternion": {"W": -0.5500654029475707, "X": 0.0, "Y": 0.0, "Z": -0.8351215794602165}, "chs": 1.0}, {"number": 3, "position": {"X": 73.285, "Y": -1504.459, "Z": 28.296, "_padding": 0}, "quaternion": {"W": 0.3847544972509717, "X": 0.0, "Y": 0.0, "Z": -0.9230189471755994}, "chs": 1.0}, {"number": 4, "position": {"X": 151.461, "Y": -1581.154, "Z": 28.336, "_padding": 0}, "quaternion": {"W": 0.46682658986353703, "X": 0.0, "Y": 0.0, "Z": -0.8843488762905627}, "chs": 1.0}, {"number": 5, "position": {"X": 271.806, "Y": -1668.824, "Z": 28.365, "_padding": 0}, "quaternion": {"W": -0.2448251351727337, "X": 0.0, "Y": 0.0, "Z": -0.9695672504719065}, "chs": 1.0}, {"number": 6, "position": {"X": 199.449, "Y": -1744.965, "Z": 27.975, "_padding": 0}, "quaternion": {"W": -0.39348466564283785, "X": 0.0, "Y": 0.0, "Z": -0.9193311796648388}, "chs": 1.0}, {"number": 7, "position": {"X": 64.075, "Y": -1898.786, "Z": 20.646, "_padding": 0}, "quaternion": {"W": -0.8459279987562022, "X": 0.0, "Y": 0.0, "Z": -0.5332971225502036}, "chs": 1.0}, {"number": 8, "position": {"X": -8.708, "Y": -1845.058, "Z": 23.926, "_padding": 0}, "quaternion": {"W": -0.9016174872552226, "X": 0.0, "Y": 0.0, "Z": -0.43253428381525827}, "chs": 1.0}, {"number": 9, "position": {"X": -103.686, "Y": -1759.231, "Z": 28.683, "_padding": 0}, "quaternion": {"W": -0.9866532809622274, "X": 0.0, "Y": 0.0, "Z": 0.16283520247929173}, "chs": 1.0}, {"number": 10, "position": {"X": 66.176, "Y": -1662.367, "Z": 28.218, "_padding": 0}, "quaternion": {"W": -0.8680125502147097, "X": 0.0, "Y": 0.0, "Z": 0.49654225668089536}, "chs": 1.0}, {"number": 11, "position": {"X": 263.063, "Y": -1551.714, "Z": 28.343, "_padding": 0}, "quaternion": {"W": -0.8680125502147097, "X": 0.0, "Y": 0.0, "Z": 0.49654225668089536}, "chs": 1.0}, {"number": 12, "position": {"X": 445.223, "Y": -1449.641, "Z": 28.344, "_padding": 0}, "quaternion": {"W": -0.8113546876046748, "X": 0.0, "Y": 0.0, "Z": 0.5845541642157044}, "chs": 1.0}, {"number": 13, "position": {"X": 628.25, "Y": -1441.992, "Z": 29.396, "_padding": 0}, "quaternion": {"W": -0.7221044238456826, "X": 0.0, "Y": 0.0, "Z": 0.6917840711251558}, "chs": 1.0}, {"number": 14, "position": {"X": 784.386, "Y": -1444.13, "Z": 26.088, "_padding": 0}, "quaternion": {"W": -0.2118109553689918, "X": 0.0, "Y": 0.0, "Z": 0.9773106564371816}, "chs": 1.0}, {"number": 15, "position": {"X": 838.221, "Y": -1578.565, "Z": 29.677, "_padding": 0}, "quaternion": {"W": 0.002993235197524504, "X": 0.0, "Y": 0.0, "Z": 0.9999955202614921}, "chs": 1.0}, {"number": 16, "position": {"X": 816.763, "Y": -1736.237, "Z": 28.339, "_padding": 0}, "quaternion": {"W": 0.6816344865980473, "X": 0.0, "Y": 0.0, "Z": 0.73169284995838}, "chs": 1.0}, {"number": 17, "position": {"X": 721.471, "Y": -1738.39, "Z": 28.408, "_padding": 0}, "quaternion": {"W": -0.754383150749949, "X": 0.0, "Y": 0.0, "Z": -0.656434354573692}, "chs": 1.0}], "description": null, "lapMode": true, "name": "Crossing Paths", "numCheckpoints": 18, "version": "v3.0", "spawn": {"X": 725.306, "Y": -1743.469, "Z": 28.413, "_padding": 0}}