{"checkpoints": [{"number": 0, "position": {"X": 235.424, "Y": -849.083, "Z": 29.004, "_padding": 0}, "quaternion": {"W": 0.6090521672991526, "X": 0.0, "Y": 0.0, "Z": -0.79313016429096}}, {"number": 1, "position": {"X": 429.193, "Y": -857.492, "Z": 28.856, "_padding": 0}, "quaternion": {"W": 0.7046342099635946, "X": 0.0, "Y": 0.0, "Z": -0.7095707365365209}}, {"number": 2, "position": {"X": 666.322, "Y": -856.845, "Z": 42.041, "_padding": 0}, "quaternion": {"W": 0.7217602280983623, "X": 0.0, "Y": 0.0, "Z": -0.6921431738704068}}, {"number": 3, "position": {"X": 933.974, "Y": -853.073, "Z": 42.655, "_padding": 0}, "quaternion": {"W": 0.27563735581699916, "X": 0.0, "Y": 0.0, "Z": -0.9612616959383189}}, {"number": 4, "position": {"X": 989.758, "Y": -1048.602, "Z": 40.604, "_padding": 0}, "quaternion": {"W": -0.3123349185122325, "X": 0.0, "Y": 0.0, "Z": -0.9499720515246526}}, {"number": 5, "position": {"X": 925.535, "Y": -1086.793, "Z": 33.278, "_padding": 0}, "quaternion": {"W": -0.7120260459909964, "X": 0.0, "Y": 0.0, "Z": -0.7021530529951625}}, {"number": 6, "position": {"X": 791.837, "Y": -1095.128, "Z": 27.781, "_padding": 0}, "quaternion": {"W": 0.08019892432885888, "X": 0.0, "Y": 0.0, "Z": -0.9967788784562471}}, {"number": 7, "position": {"X": 810.067, "Y": -1239.131, "Z": 25.3, "_padding": 0}, "quaternion": {"W": -0.661311865323652, "X": 0.0, "Y": 0.0, "Z": 0.7501110696304594}}, {"number": 8, "position": {"X": 871.969, "Y": -1292.756, "Z": 32.66, "_padding": 0}, "quaternion": {"W": 0.12879559657756282, "X": 0.0, "Y": 0.0, "Z": 0.9916711623830904}}, {"number": 9, "position": {"X": 770.009, "Y": -1347.64, "Z": 38.905, "_padding": 0}, "quaternion": {"W": 0.7241718614374675, "X": 0.0, "Y": 0.0, "Z": 0.6896195437356698}}, {"number": 10, "position": {"X": 695.52, "Y": -1289.599, "Z": 41.245, "_padding": 0}, "quaternion": {"W": 0.9876883405951378, "X": 0.0, "Y": 0.0, "Z": -0.15643446504023087}}, {"number": 11, "position": {"X": 771.281, "Y": -1220.837, "Z": 44.305, "_padding": 0}, "quaternion": {"W": 0.7095707365365209, "X": 0.0, "Y": 0.0, "Z": -0.7046342099635946}}, {"number": 12, "position": {"X": 979.299, "Y": -1208.916, "Z": 42.301, "_padding": 0}, "quaternion": {"W": 0.8348478632634065, "X": 0.0, "Y": 0.0, "Z": -0.5504807400849955}}, {"number": 13, "position": {"X": 1074.86, "Y": -1037.056, "Z": 35.249, "_padding": 0}, "quaternion": {"W": 0.99556196460308, "X": 0.0, "Y": 0.0, "Z": 0.09410831331851433}}, {"number": 14, "position": {"X": 987.399, "Y": -821.492, "Z": 33.072, "_padding": 0}, "quaternion": {"W": 0.9612616959383189, "X": 0.0, "Y": 0.0, "Z": 0.27563735581699916}}, {"number": 15, "position": {"X": 898.735, "Y": -700.95, "Z": 41.582, "_padding": 0}, "quaternion": {"W": 0.9077774785329087, "X": 0.0, "Y": 0.0, "Z": 0.4194520824461771}}, {"number": 16, "position": {"X": 706.766, "Y": -571.003, "Z": 35.415, "_padding": 0}, "quaternion": {"W": 0.8517269341430477, "X": 0.0, "Y": 0.0, "Z": 0.5239859059700791}}, {"number": 17, "position": {"X": 610.62, "Y": -514.039, "Z": 45.904, "_padding": 0}, "quaternion": {"W": 0.9408807689542255, "X": 0.0, "Y": 0.0, "Z": 0.3387379202452914}}, {"number": 18, "position": {"X": 595.859, "Y": -381.914, "Z": 42.621, "_padding": 0}, "quaternion": {"W": 0.7193398003386512, "X": 0.0, "Y": 0.0, "Z": -0.6946583704589973}}, {"number": 19, "position": {"X": 693.002, "Y": -376.819, "Z": 40.203, "_padding": 0}, "quaternion": {"W": 0.8231363685344418, "X": 0.0, "Y": 0.0, "Z": -0.5678437450531013}}, {"number": 20, "position": {"X": 942.388, "Y": -315.328, "Z": 65.984, "_padding": 0}, "quaternion": {"W": 0.9384930227595559, "X": 0.0, "Y": 0.0, "Z": -0.34529819899853464}}, {"number": 21, "position": {"X": 1022.309, "Y": -208.148, "Z": 69.228, "_padding": 0}, "quaternion": {"W": -0.529919264233205, "X": 0.0, "Y": 0.0, "Z": 0.848048096156426}}, {"number": 22, "position": {"X": 1143.415, "Y": -253.547, "Z": 68.138, "_padding": 0}, "quaternion": {"W": -0.5821229701572892, "X": 0.0, "Y": 0.0, "Z": 0.8131007610470278}}], "description": null, "lapMode": false, "name": "Lost and Found", "numCheckpoints": 23, "version": "v3.0", "spawn": {"X": 232.238, "Y": -843.581, "Z": 29.115, "_padding": 0}, "dhprops": []}